perlin_numpy/__init__.py
perlin_numpy/perlin2d.py
perlin_numpy/perlin3d.py
perlin_numpy-0.0.1.dist-info/LICENSE
perlin_numpy-0.0.1.dist-info/METADATA
perlin_numpy-0.0.1.dist-info/WHEEL
perlin_numpy-0.0.1.dist-info/top_level.txt
perlin_numpy-0.0.1.dist-info/RECORD
