Metadata-Version: 2.1
Name: perlin-numpy
Version: 0.0.1
Author: Pierre Vigier
Maintainer: Martin Cejp
License: MIT License
Project-URL: Documentation, https://perlin-numpy.readthedocs.io/
Project-URL: Repository, https://github.com/pvigier/perlin-numpy
Requires-Python: >=3
License-File: LICENSE
Requires-Dist: numpy>=1.15
Provides-Extra: docs
Requires-Dist: sphinx; extra == "docs"
Requires-Dist: sphinx_rtd_theme; extra == "docs"
